vallog/__init__.py
vallog/logger.py
vallog/timer.py
vallog-0.3.2.dist-info/licenses/LICENSE
vallog-0.3.2.dist-info/METADATA
vallog-0.3.2.dist-info/WHEEL
vallog-0.3.2.dist-info/top_level.txt
vallog-0.3.2.dist-info/RECORD
